sdk-verilog/spikeling_neurons.v
// Auto-generated from profile.spk by spikeling_verilog.py
// Each neuron is a hardware register with comparator + refractory counter.
// Synthesizable; also runnable in Icarus Verilog / Verilator.

module spikeling_neurons #(
    parameter P_WIDTH = 16,
    parameter R_WIDTH = 16
) (
    input  wire                 clk,
    input  wire                 rst,
    // per-neuron input current this tick (packed)
    input  wire [P_WIDTH-1:0]   stim   [0:1],
    // 1-bit spike output per neuron
    output reg                  spike  [0:1]
);

    // -- neuron parameters (constants from the .spk) --
    localparam integer NEURON_COUNT = 2;
    localparam integer REFR_TICKS   = 400;

    // thresholds
    localparam [P_WIDTH-1:0] TH_0 = 110; // LeftMic
    localparam [P_WIDTH-1:0] TH_1 = 110; // RightMic
    // leaks (membrane decay per tick)
    localparam [P_WIDTH-1:0] LK_0 = 5; // LeftMic
    localparam [P_WIDTH-1:0] LK_1 = 5; // RightMic

    // -- state registers: THESE ARE THE NEURONS --
    reg [P_WIDTH-1:0] p    [0:1];  // membrane potential
    reg [R_WIDTH-1:0] refr [0:1];  // refractory countdown

    integer i;

    // helper: threshold/leak lookup as functions of index
    function [P_WIDTH-1:0] thresh_of;
        input integer idx;
        begin
            case (idx)
                0: thresh_of = TH_0;
                1: thresh_of = TH_1;
                default: thresh_of = {P_WIDTH{1'b1}};
            endcase
        end
    endfunction

    function [P_WIDTH-1:0] leak_of;
        input integer idx;
        begin
            case (idx)
                0: leak_of = LK_0;
                1: leak_of = LK_1;
                default: leak_of = 0;
            endcase
        end
    endfunction

    // -- parallel neuron update: every neuron advances each clock --
    always @(posedge clk) begin
        if (rst) begin
            for (i = 0; i < NEURON_COUNT; i = i + 1) begin
                p[i]     <= 0;
                refr[i]  <= 0;
                spike[i] <= 1'b0;
            end
        end else begin
            for (i = 0; i < NEURON_COUNT; i = i + 1) begin
                spike[i] <= 1'b0;          // default: no spike
                if (refr[i] != 0) begin
                    refr[i] <= refr[i] - 1; // in refractory: just count down
                end else begin
                    // leaky integration
                    if (p[i] > leak_of(i))
                        p[i] <= p[i] - leak_of(i) + stim[i];
                    else
                        p[i] <= stim[i];
                    // threshold compare on the *post-update* estimate
                    if ((((p[i] > leak_of(i)) ? p[i] - leak_of(i) : 0) + stim[i])
                         >= thresh_of(i)) begin
                        p[i]     <= 0;            // reset
                        refr[i]  <= REFR_TICKS;   // enter refractory
                        spike[i] <= 1'b1;         // FIRE
                    end
                end
            end
        end
    end

endmodule

sdk-verilog/spikeling_tb.v
// Testbench for spikeling_neurons.
// Drives stimulus, prints spikes, dumps a waveform (spikeling.vcd).
`timescale 1ns/1ps

module tb;
    localparam P_WIDTH = 16;
    localparam N = `NCOUNT;   // passed in at compile time

    reg clk = 0;
    reg rst = 1;
    reg  [P_WIDTH-1:0] stim  [0:N-1];
    wire               spike [0:N-1];

    // device under test
    spikeling_neurons #(.P_WIDTH(P_WIDTH)) dut (
        .clk(clk), .rst(rst), .stim(stim), .spike(spike)
    );

    // 100 MHz clock
    always #5 clk = ~clk;

    integer i, t;
    integer total_spikes = 0;

    // simple LFSR for varied stimulus
    reg [31:0] lfsr = 32'hACE12345;
    function [31:0] next_rand;
        input [31:0] s;
        begin
            next_rand = s ^ (s << 13);
            next_rand = next_rand ^ (next_rand >> 17);
            next_rand = next_rand ^ (next_rand << 5);
        end
    endfunction

    initial begin
        $dumpfile("spikeling.vcd");
        $dumpvars(0, tb);

        for (i = 0; i < N; i = i + 1) stim[i] = 0;

        // hold reset 2 cycles
        @(posedge clk); @(posedge clk);
        rst = 0;

        // run 200 ticks of stimulus
        for (t = 0; t < 200; t = t + 1) begin
            for (i = 0; i < N; i = i + 1) begin
                lfsr = next_rand(lfsr);
                // intensity 0..63
                stim[i] = lfsr[5:0];
            end
            @(posedge clk);
            // sample spikes (registered, so check after edge settles)
            #1;
            for (i = 0; i < N; i = i + 1) begin
                if (spike[i]) begin
                    total_spikes = total_spikes + 1;
                    if (total_spikes <= 20)
                        $display("  t=%0d  neuron %0d FIRED", t, i);
                end
            end
        end

        $display("");
        $display("Total spikes over 200 ticks across %0d neurons: %0d",
                 N, total_spikes);
        $display("Waveform written to spikeling.vcd (open in GTKWave).");
        $finish;
    end
endmodule

sdk-verilog/spikeling.vcd
$date
	Sat Jun 20 02:06:41 2026
$end
$version
	Icarus Verilog
$end
$timescale
	1ps
$end
$scope module tb $end
$var parameter 32 ! N $end
$var parameter 32 " P_WIDTH $end
$var reg 1 # clk $end
$var reg 32 $ lfsr [31:0] $end
$var reg 1 % rst $end
$var integer 32 & i [31:0] $end
$var integer 32 ' t [31:0] $end
$var integer 32 ( total_spikes [31:0] $end
$scope function next_rand $end
$var reg 32 ) s [31:0] $end
$upscope $end
$scope module dut $end
$var wire 1 # clk $end
$var wire 1 % rst $end
$var parameter 16 * LK_0 $end
$var parameter 16 + LK_1 $end
$var parameter 32 , NEURON_COUNT $end
$var parameter 32 - P_WIDTH $end
$var parameter 32 . REFR_TICKS $end
$var parameter 32 / R_WIDTH $end
$var parameter 16 0 TH_0 $end
$var parameter 16 1 TH_1 $end
$var integer 32 2 i [31:0] $end
$scope function leak_of $end
$var integer 32 3 idx [31:0] $end
$upscope $end
$scope function thresh_of $end
$var integer 32 4 idx [31:0] $end
$upscope $end
$upscope $end
$upscope $end
$enddefinitions $end
$comment Show the parameter values. $end
$dumpall
b1101110 1
b1101110 0
b10000 /
b110010000 .
b10000 -
b10 ,
b101 +
b101 *
b10000 "
b10 !
$end
#0
$dumpvars
bx 4
bx 3
bx 2
bx )
b0 (
bx '
b10 &
1%
b10101100111000010010001101000101 $
0#
$end
#5000
b10 2
1#
#10000
0#
#15000
b10111111111100110100011101011 $
b10011001101100010010011100100001 )
b10 &
b0 '
0%
b10 2
1#
#20000
0#
#25000
b1 4
b1 3
b10 2
1#
#26000
b11110110110000011011011011110000 $
b10000110100011111101011011011010 )
b1 '
b10 &
#30000
0#
#35000
b1 4
b1 3
b10 2
1#
#36000
b111010000111011101011111111100 $
b11000011111001010000100100011111 )
b10 '
b10 &
#40000
0#
#45000
b1 4
b1 3
b10 2
1#
#46000
b10001100110001011100010111111111 $
b10011100101000001110011000101101 )
b11 '
b1 (
b10 &
#50000
0#
#55000
b0 4
b0 3
b10 2
1#
#56000
b1111010011111010100101011100100 $
b10111011001111011100011110000010 )
b100 '
b10 (
b10 &
#60000
0#
#65000
b10 2
1#
#66000
b11011011110000100001111010000001 $
b10110111000101011100110111110100 )
b101 '
b10 &
#70000
0#
#75000
b10 2
1#
#76000
b11011011100010001011111101011110 $
b10011010010111000010001110001000 )
b110 '
b10 &
#80000
0#
#85000
b10 2
1#
#86000
b10010100101011110000111100100111 $
b1000000000000000011010010001111 )
b111 '
b10 &
#90000
0#
#95000
b10 2
1#
#96000
b11100001101000101110110101000110 $
b11011100001100010110010111000010 )
b1000 '
b10 &
#100000
0#
#105000
b10 2
1#
#106000
b1111010001001001010001001010011 $
b111101010001000001101100100011 )
b1001 '
b10 &
#110000
0#
#115000
b10 2
1#
#116000
b110000000101011011110101100110 $
b100011101110000001100111100100 )
b1010 '
b10 &
#120000
0#
#125000
b10 2
1#
#126000
b11001100111100001101001101010 $
b1110000100111101110100111111010 )
b1011 '
b10 &
#130000
0#
#135000
b10 2
1#
#136000
b1110001011011001110001110101111 $
b10000000101101011101011101100011 )
b1100 '
b10 &
#140000
0#
#145000
b10 2
1#
#146000
b110111111000101000001011001100 $
b1001110001101111101000101000011 )
b1101 '
b10 &
#150000
0#
#155000
b10 2
1#
#156000
b1100101110111100110011111101100 $
b10010000110111010001001100110001 )
b1110 '
b10 &
#160000
0#
#165000
b10 2
1#
#166000
b11101111000000101001000011111010 $
b10001101010101011101110011011101 )
b1111 '
b10 &
#170000
0#
#175000
b10 2
1#
#176000
b1000000111000111111111000001101 $
b11110101011000100000011110100 )
b10000 '
b10 &
#180000
0#
#185000
b10 2
1#
#186000
b110000000111101010100110001000 $
b11011011011010100111001000011100 )
b10001 '
b10 &
#190000
0#
#195000
b10 2
1#
#196000
b101110101011010101000001011010 $
b1000000110101001011100011111111 )
b10010 '
b10 &
#200000
0#
#205000
b10 2
1#
#206000
b11010011001001100011111110001101 $
b10000011011000001001100101001 )
b10011 '
b10 &
#210000
0#
#215000
b10 2
1#
#216000
b1001011001111100110100001100110 $
b10001110001001010010100100100110 )
b10100 '
b10 &
#220000
0#
#225000
b10 2
1#
#226000
b10101111011110111010000011000001 $
b1000000011011111000010010011111 )
b10101 '
b10 &
#230000
0#
#235000
b10 2
1#
#236000
b10010001011111111110010111001000 $
b10110111000111100100001101110000 )
b10110 '
b10 &
#240000
0#
#245000
b10 2
1#
#246000
b111001011010110000001110000001 $
b11010101000111001011011001001011 )
b10111 '
b10 &
#250000
0#
#255000
b10 2
1#
#256000
b11010010110001001101011001111001 $
b1111010011110101110111010001100 )
b11000 '
b10 &
#260000
0#
#265000
b10 2
1#
#266000
b100011000010100011001111111011 $
b1001001011100011001110111111100 )
b11001 '
b10 &
#270000
0#
#275000
b10 2
1#
#276000
b10111100010101100001101101111011 $
b11001011110110010100100101100001 )
b11010 '
b10 &
#280000
0#
#285000
b10 2
1#
#286000
b11000001001111000101100001101111 $
b10011000000100011101100000000111 )
b11011 '
b10 &
#290000
0#
#295000
b10 2
1#
#296000
b100011011100010001101001111 $
b1100000000100011001110010111 )
b11100 '
b10 &
#300000
0#
#305000
b10 2
1#
#306000
b10001100111010001101010100111001 $
b11000000111100111100101011001100 )
b11101 '
b10 &
#310000
0#
#315000
b10 2
1#
#316000
b1010000011100010010111000111111 $
b1011111101110000111110111011110 )
b11110 '
b10 &
#320000
0#
#325000
b10 2
1#
#326000
b10111101010110010110010110 $
b11000011011010000110100001100100 )
b11111 '
b10 &
#330000
0#
#335000
b10 2
1#
#336000
b10101010111101000110000001000 $
b1100110101110011010010000010101 )
b100000 '
b10 &
#340000
0#
#345000
b10 2
1#
#346000
b1110101001010110010100011111110 $
b1011111001000100010001010000111 )
b100001 '
b10 &
#350000
0#
#355000
b10 2
1#
#356000
b101101101010110110011000110110 $
b10110101010001111110001100100 )
b100010 '
b10 &
#360000
0#
#365000
b10 2
1#
#366000
b111101010111000010101000110 $
b1101100110111010101011010000000 )
b100011 '
b10 &
#370000
0#
#375000
b10 2
1#
#376000
b1110110101000001011100110010011 $
b10010111011011001010011000100111 )
b100100 '
b10 &
#380000
0#
#385000
b10 2
1#
#386000
b11011010000101100010110001011100 $
b1010011110011111100001000011010 )
b100101 '
b10 &
#390000
0#
#395000
b10 2
1#
#396000
b10100011011001010000110111011 $
b11101100001010011101000111010010 )
b100110 '
b10 &
#400000
0#
#405000
b10 2
1#
#406000
b1010101011000001011001100110110 $
b10001011001010111011001101010110 )
b100111 '
b10 &
#410000
0#
#415000
b10 2
1#
#416000
b11001010100100000100001111110010 $
b100011110011000000010000010101 )
b101000 '
b10 &
#420000
0#
#425000
b10 2
1#
#426000
b11110101101110010010110001010110 $
b10011111001000100011001000100101 )
b101001 '
b10 &
#430000
0#
#435000
b10 2
1#
#436000
b1001001001000000111110011010100 $
b11010110010000110000110110101111 )
b101010 '
b10 &
#440000
0#
#445000
b10 2
1#
#446000
b110010101111101100001011010011 $
b10010001111000010010111010101001 )
b101011 '
b10 &
#450000
0#
#455000
b10 2
1#
#456000
b110011110010010110101001000110 $
b10110110011111100010001110000001 )
b101100 '
b10 &
#460000
0#
#465000
b10 2
1#
#466000
b10101111101100111010101011000000 $
b11001110101101010000010111000110 )
b101101 '
b10 &
#470000
0#
#475000
b10 2
1#
#476000
b11010111100011011101100001101101 $
b10000111100100110011000100010101 )
b101110 '
b10 &
#480000
0#
#485000
b10 2
1#
#486000
b1110010111100011110001101010001 $
b11111100100010011000101110001101 )
b101111 '
b10 &
#490000
0#
#495000
b10 2
1#
#496000
b1010011100011110011110111010110 $
b10011101111001110110011110011100 )
b110000 '
b10 &
#500000
0#
#505000
b10 2
1#
#506000
b110000010100101000111111101000 $
b110010100000010101111001001100 )
b110001 '
b10 &
#510000
0#
#515000
b10 2
1#
#516000
b10110111001100010111100010111110 $
b1010100010110000101100011011111 )
b110010 '
b10 &
#520000
0#
#525000
b10 2
1#
#526000
b10001011111010001010010101000001 $
b10011100111110000110000100001101 )
b110011 '
b10 &
#530000
0#
#535000
b10 2
1#
#536000
b11110101101100110001010000100001 $
b1110111010110011001011011000001 )
b110100 '
b10 &
#540000
0#
#545000
b10 2
1#
#546000
b1111000001110001110101110111001 $
b1110001110110001000100011111010 )
b110101 '
b10 &
#550000
0#
#555000
b10 2
1#
#556000
b101010100001010101010001001011 $
b11001100101100001101101011011110 )
b110110 '
b10 &
#560000
0#
#565000
b10 2
1#
#566000
b11001110110010110110010110010 $
b10000001100000101111110111101101 )
b110111 '
b10 &
#570000
0#
#575000
b10 2
1#
#576000
b10100100110011111001000011100010 $
b10111101101010011110010000110101 )
b111000 '
b10 &
#580000
0#
#585000
b10 2
1#
#586000
b10100011110011010110011001110011 $
b10001100101011001000101011101011 )
b111001 '
b10 &
#590000
0#
#595000
b10 2
1#
#596000
b10011010001100100100010011111000 $
b11101111011000110011111110110010 )
b111010 '
b10 &
#600000
0#
#605000
b10 2
1#
#606000
b10100101001110101111111101100 $
b10000111000010001001100001101110 )
b111011 '
b10 &
#610000
0#
#615000
b10 2
1#
#616000
b11100001010111111111010011100000 $
b10100000011101010100001100001 )
b111100 '
b10 &
#620000
0#
#625000
b10 2
1#
#626000
b11101111110010001010100011101101 $
b11100111101111001001101100100001 )
b111101 '
b10 &
#630000
0#
#635000
b10 2
1#
#636000
b11000010001111100110100010001100 $
b10100000011110111100010101100111 )
b111110 '
b10 &
#640000
0#
#645000
b10 2
1#
#646000
b11000000111110100000001101110101 $
b11101010110100100000110001111011 )
b111111 '
b10 &
#650000
0#
#655000
b10 2
1#
#656000
b11010000111101111001011101010110 $
b10010010000010001000010011011111 )
b1000000 '
b10 &
#660000
0#
#665000
b10 2
1#
#666000
b11010011110000100100111110110111 $
b1100001101101011000110101011000 )
b1000001 '
b10 &
#670000
0#
#675000
b10 2
1#
#676000
b10000011011001110011011100001001 $
b11011100101010001011011100001101 )
b1000010 '
b10 &
#680000
0#
#685000
b10 2
1#
#686000
b1011100101000000110001110000011 $
b11010101010000101001110010001010 )
b1000011 '
b10 &
#690000
0#
#695000
b10 2
1#
#696000
b11100000100011001001011110101001 $
b1001010110101010101011010001011 )
b1000100 '
b10 &
#700000
0#
#705000
b10 2
1#
#706000
b11101111000100100000110100010010 $
b111101010010000101110000110101 )
b1000101 '
b10 &
#710000
0#
#715000
b10 2
1#
#716000
b1001000100100010101011000000011 $
b1111000101100110101001100001010 )
b1000110 '
b10 &
#720000
0#
#725000
b10 2
1#
#726000
b10010011001010011000001010110111 $
b101000011100011110001001001011 )
b1000111 '
b10 &
#730000
0#
#735000
b10 2
1#
#736000
b111101110111000000110111100100 $
b11001100100110010101001000001000 )
b1001000 '
b10 &
#740000
0#
#745000
b10 2
1#
#746000
b11001111010100110110010001111100 $
b110000011110101010100101010100 )
b1001001 '
b10 &
#750000
0#
#755000
b10 2
1#
#756000
b10001110101100010111101011001010 $
b11011000010010100000011111010010 )
b1001010 '
b10 &
#760000
0#
#765000
b10 2
1#
#766000
b10010000001001101101100110011 $
b10011100111001010010110111111110 )
b1001011 '
b10 &
#770000
0#
#775000
b10 2
1#
#776000
b10011100011011001111100110100000 $
b10100101001111010000111111000010 )
b1001100 '
b10 &
#780000
0#
#785000
b10 2
1#
#786000
b1111001101100000111010011010111 $
b1101000010001111111100110001100 )
b1001101 '
b10 &
#790000
0#
#795000
b10 2
1#
#796000
b101001011110000111001111101101 $
b10010010011111110100011100000010 )
b1001110 '
b10 &
#800000
0#
#805000
b10 2
1#
#806000
b10111111100011100100001110101001 $
b11000111101111011100110110001111 )
b1001111 '
b10 &
#810000
0#
#815000
b10 2
1#
#816000
b11011011100110001110010110010001 $
b10001000100100000101001011010100 )
b1010000 '
b10 &
#820000
0#
#825000
b10 2
1#
#826000
b111011011111001010101110110011 $
b100010011111100110011010000100 )
b1010001 '
b10 &
#830000
0#
#835000
b10 2
1#
#836000
b10001100111010100100001011011101 $
b1101111010110010000101001110110 )
b1010010 '
b10 &
#840000
0#
#845000
b10 2
1#
#846000
b1110000001001010000110010000111 $
b1010010100000011001000000100101 )
b1010011 '
b10 &
#850000
0#
#855000
b10 2
1#
#856000
b10011001101010110001110010000000 $
b11100111000001010000111111111101 )
b1010100 '
b10 &
#860000
0#
#865000
b10 2
1#
#866000
b10110101000010111110111100010101 $
b10111101010101110101001000111101 )
b1010101 '
b10 &
#870000
0#
#875000
b10 2
1#
#876000
b11111001101011010111001110110011 $
b11010101110011000100011101000001 )
b1010110 '
b10 &
#880000
0#
#885000
b10 2
1#
#886000
b1110011001100110011100111011001 $
b10101100101111000011001110011110 )
b1010111 '
b10 &
#890000
0#
#895000
b10 2
1#
#896000
b11011000101100010010101110011111 $
b10010101000010100110100001111101 )
b1011000 '
b10 &
#900000
0#
#905000
b10 2
1#
#906000
b11110101101001000001000111111 $
b1000101100101000001101010111110 )
b1011001 '
b10 &
#910000
0#
#915000
b10 2
1#
#916000
b10000101110001001011111110110101 $
b1010000100101111000110110000110 )
b1011010 '
b10 &
#920000
0#
#925000
b10 2
1#
#926000
b11001110101110011100000111100110 $
b1010100011100001100001100101100 )
b1011011 '
b10 &
#930000
0#
#935000
b10 2
1#
#936000
b11110001111010110010110110011 $
b100110001010100010111000100100 )
b1011100 '
b10 &
#940000
0#
#945000
b10 2
1#
#946000
b10001111011010011000001101000101 $
b11100011111000001100001000110110 )
b1011101 '
b10 &
#950000
0#
#955000
b10 2
1#
#956000
b11110111111000101011001100110100 $
b1011111001011101110010001100101 )
b1011110 '
b10 &
#960000
0#
#965000
b10 2
1#
#966000
b11000111011111000001100001000001 $
b10010001000010000001110100110110 )
b1011111 '
b10 &
#970000
0#
#975000
b10 2
1#
#976000
b101010110100001000001100010001 $
b11001010111101110101010100011011 )
b1100000 '
b10 &
#980000
0#
#985000
b10 2
1#
#986000
b10000011100011101101111110001110 $
b1101100111001010111011101001000 )
b1100001 '
b10 &
#990000
0#
#995000
b10 2
1#
#996000
b10011010010000000001101010000100 $
b1010111100110010100010110010001 )
b1100010 '
b10 &
#1000000
0#
#1005000
b10 2
1#
#1006000
b11000110100001101000010101010001 $
b10111011000010100001011110001100 )
b1100011 '
b10 &
#1010000
0#
#1015000
b10 2
1#
#1016000
b10010110100101101101100110001 $
b11010011101110010110011010100111 )
b1100100 '
b10 &
#1020000
0#
#1025000
b10 2
1#
#1026000
b11110100101111111110100110110100 $
b1111111001011110010001010001011 )
b1100101 '
b10 &
#1030000
0#
#1035000
b10 2
1#
#1036000
b10111001100110001111000110110101 $
b111000101001001100001101110000 )
b1100110 '
b10 &
#1040000
0#
#1045000
b10 2
1#
#1046000
b11101110111000100011110100010111 $
b1010010011011100100111000100010 )
b1100111 '
b10 &
#1050000
0#
#1055000
b10 2
1#
#1056000
b1100001110110111000010101001010 $
b10000001010100011011111101010111 )
b1101000 '
b10 &
#1060000
0#
#1065000
b10 2
1#
#1066000
b1111010011111100101110011011111 $
b111111001010110111001110010011 )
b1101001 '
b10 &
#1070000
0#
#1075000
b10 2
1#
#1076000
b10001100011110101011011000011001 $
b10001101010110010110000110001101 )
b1101010 '
b10 &
#1080000
0#
#1085000
b10 2
1#
#1086000
b10100000101110011001111100011000 $
b10001101100001101001001111100101 )
b1101011 '
b10 &
#1090000
0#
#1095000
b10 2
1#
#1096000
b11111000010110010101111010010100 $
b11111000000000000000000000010101 )
b1101100 '
b10 &
#1100000
0#
#1105000
b10 2
1#
#1106000
b100011001111000100001011011000 $
b10100010111111010101110101110001 )
b1101101 '
b10 &
#1110000
0#
#1115000
b10 2
1#
#1116000
b1100000010100000110101101001001 $
b11000111100001011111101000001011 )
b1101110 '
b10 &
#1120000
0#
#1125000
b10 2
1#
#1126000
b1001101111101011010111100101001 $
b11001010000101101100011101110101 )
b1101111 '
b10 &
#1130000
0#
#1135000
b10 2
1#
#1136000
b110101001110101100110110110110 $
b11111010000011101001011100000001 )
b1110000 '
b10 &
#1140000
0#
#1145000
b10 2
1#
#1146000
b100011000101001110101001101010 $
b11111101000010110100010111110000 )
b1110001 '
b10 &
#1150000
0#
#1155000
b10 2
1#
#1156000
b1000100001011011000111101001101 $
b1110101011001110101110110000110 )
b1110010 '
b10 &
#1160000
0#
#1165000
b10 2
1#
#1166000
b10111001101011100101010101101100 $
b1001101010011101110000001001111 )
b1110011 '
b10 &
#1170000
0#
#1175000
b10 2
1#
#1176000
b1110111101000000100001100100110 $
b10011011111100111000101001101 )
b1110100 '
b10 &
#1180000
0#
#1185000
b10 2
1#
#1186000
b10011000101000010110000010001001 $
b10000111010100110010010001000100 )
b1110101 '
b10 &
#1190000
0#
#1195000
b10 2
1#
#1196000
b11111000001011111000101000111 $
b100010101100110100000011110001 )
b1110110 '
b10 &
#1200000
0#
#1205000
b10 2
1#
#1206000
b1010100100100101000111110001100 $
b10000100100001010111101111110001 )
b1110111 '
b10 &
#1210000
0#
#1215000
b10 2
1#
#1216000
b1110110011111111110001000010101 $
b10101001000000101010101010011101 )
b1111000 '
b10 &
#1220000
0#
#1225000
b10 2
1#
#1226000
b1011011010001110110011010100011 $
b11001101100111011110011001101011 )
b1111001 '
b10 &
#1230000
0#
#1235000
b10 2
1#
#1236000
b100100010011100010011101010100 $
b1000101111110001111000000101010 )
b1111010 '
b10 &
#1240000
0#
#1245000
b10 2
1#
#1246000
b1101010000110110011101000000101 $
b11110100001111100011011111000110 )
b1111011 '
b10 &
#1250000
0#
#1255000
b10 2
1#
#1256000
b1000100101101100001111011100110 $
b10100110001010000000100110101000 )
b1111100 '
b10 &
#1260000
0#
#1265000
b10 2
1#
#1266000
b11010111001100010101101011011100 $
b1101010001110010011011100110011 )
b1111101 '
b10 &
#1270000
0#
#1275000
b10 2
1#
#1276000
b1110110111011110001101110001010 $
b1110001001111100011100111001001 )
b1111110 '
b10 &
#1280000
0#
#1285000
b10 2
1#
#1286000
b10001101011110011110001111110101 $
b100110010111000011100111100101 )
b1111111 '
b10 &
#1290000
0#
#1295000
b10 2
1#
#1296000
b11110101000001011111100111111111 $
b10010001111001000111010110110110 )
b10000000 '
b10 &
#1300000
0#
#1305000
b10 2
1#
#1306000
b10010100010111100011111011010110 $
b1101011111011010000010100010 )
b10000001 '
b10 &
#1310000
0#
#1315000
b10 2
1#
#1316000
b1010000001101000010111100000010 $
b100011000111100011010110010100 )
b10000010 '
b10 &
#1320000
0#
#1325000
b10 2
1#
#1326000
b11110001011100010101110101001100 $
b1101111010101001011100011101000 )
b10000011 '
b10 &
#1330000
0#
#1335000
b10 2
1#
#1336000
b10111110000110010110111100100101 $
b10000001110011101011010000100000 )
b10000100 '
b10 &
#1340000
0#
#1345000
b10 2
1#
#1346000
b10111000101110011101011010000110 $
b11101100010011010101110110111011 )
b10000101 '
b10 &
#1350000
0#
#1355000
b10 2
1#
#1356000
b11010100110010100011010111001100 $
b11001111010000111010000111110010 )
b10000110 '
b10 &
#1360000
0#
#1365000
b10 2
1#
#1366000
b1011000100110111010010010110110 $
b11011100000011000110001001010101 )
b10000111 '
b10 &
#1370000
0#
#1375000
b10 2
1#
#1376000
b11101111100111010100010101101010 $
b10101101101000110010010010110000 )
b10001000 '
b10 &
#1380000
0#
#1385000
b10 2
1#
#1386000
b11111010011101100101001111000011 $
b10100001001101001111100010110010 )
b10001001 '
b10 &
#1390000
0#
#1395000
b10 2
1#
#1396000
b101111110111000010110000110101 $
b110001110010110101001101000100 )
b10001010 '
b10 &
#1400000
0#
#1405000
b10 2
1#
#1406000
b10110000100000011001000011001 $
b11100001000000011111101000011000 )
b10001011 '
b10 &
#1410000
0#
#1415000
b10 2
1#
#1416000
b100111011111001100100110001011 $
b11010001100000101110000110000 )
b10001100 '
b10 &
#1420000
0#
#1425000
b10 2
1#
#1426000
b1100001110000111101001001000100 $
b1110111111100110010001100001101 )
b10001101 '
b10 &
#1430000
0#
#1435000
b10 2
1#
#1436000
b10011101100000101011010101001011 $
b1101010111000001010111110100001 )
b10001110 '
b10 &
#1440000
0#
#1445000
b10 2
1#
#1446000
b1111100111100101011011010100001 $
b10101110010111011010101100011110 )
b10001111 '
b10 &
#1450000
0#
#1455000
b10 2
1#
#1456000
b10111001010101010101011100010110 $
b1101110111101101111010111110010 )
b10010000 '
b10 &
#1460000
0#
#1465000
b10 2
1#
#1466000
b1011000100110111010011010011001 $
b1100101010001000100011101101101 )
b10010001 '
b10 &
#1470000
0#
#1475000
b10 2
1#
#1476000
b1000010100100101110010111100001 $
b10100101010110101000011100011101 )
b10010010 '
b10 &
#1480000
0#
#1485000
b10 2
1#
#1486000
b111010110010101000101001110 $
b11011011111101111001010000110110 )
b10010011 '
b10 &
#1490000
0#
#1495000
b10 2
1#
#1496000
b100100110010001110110110101 $
b10000011011000000111100100110110 )
b10010100 '
b10 &
#1500000
0#
#1505000
b10 2
1#
#1506000
b1111101010110111101100010001001 $
b11000010110110100110101001100010 )
b10010101 '
b10 &
#1510000
0#
#1515000
b10 2
1#
#1516000
b10100100110101100001100111000100 $
b11001111000101011000111000101100 )
b10010110 '
b10 &
#1520000
0#
#1525000
b10 2
1#
#1526000
b10001100011100000111011101011 $
b10011010001110111110110001010011 )
b10010111 '
b10 &
#1530000
0#
#1535000
b10 2
1#
#1536000
b10011101100110100000000000010011 $
b11011010001100111101111010000010 )
b10011000 '
b10 &
#1540000
0#
#1545000
b10 2
1#
#1546000
b11010011111111011111101100100000 $
b1101110100110011101010100111111 )
b10011001 '
b10 &
#1550000
0#
#1555000
b10 2
1#
#1556000
b10000100000011101011111101110010 $
b11111111101000000110000011101100 )
b10011010 '
b10 &
#1560000
0#
#1565000
b10 2
1#
#1566000
b10001011011011000101101100110011 $
b101111111110100000011011000010 )
b10011011 '
b10 &
#1570000
0#
#1575000
b10 2
1#
#1576000
b11110100100010101101100101101111 $
b1010011010101110111110110 )
b10011100 '
b10 &
#1580000
0#
#1585000
b10 2
1#
#1586000
b10000001110010101101111001001010 $
b1011011010010101011100100111100 )
b10011101 '
b10 &
#1590000
0#
#1595000
b10 2
1#
#1596000
b1110001001010011100001010111 $
b10011010011111011001101000101011 )
b10011110 '
b10 &
#1600000
0#
#1605000
b10 2
1#
#1606000
b10000110100000000100111110000011 $
b10001100110111100001010011000000 )
b10011111 '
b10 &
#1610000
0#
#1615000
b10 2
1#
#1616000
b1011110010110110100101100010000 $
b1100001011111010110111101011011 )
b10100000 '
b10 &
#1620000
0#
#1625000
b10 2
1#
#1626000
b10111110011000010011111110110101 $
b11010000000100110100000100001100 )
b10100001 '
b10 &
#1630000
0#
#1635000
b10 2
1#
#1636000
b10000011101101000010101010100011 $
b10101011011011011011110010111110 )
b10100010 '
b10 &
#1640000
0#
#1645000
b10 2
1#
#1646000
b1100111011100100101011001111100 $
b11011010111010010111001110110011 )
b10100011 '
b10 &
#1650000
0#
#1655000
b10 2
1#
#1656000
b110011101010010001000101101110 $
b10011010000001011101010011100010 )
b10100100 '
b10 &
#1660000
0#
#1665000
b10 2
1#
#1666000
b1001111110110100100111001000001 $
b100001000111111110110000101100 )
b10100101 '
b10 &
#1670000
0#
#1675000
b10 2
1#
#1676000
b10100110000011011001111001000011 $
b11000100010111111100010001001000 )
b10100110 '
b10 &
#1680000
0#
#1685000
b10 2
1#
#1686000
b11101100000011110010011010110100 $
b10101101011110110110000010000001 )
b10100111 '
b10 &
#1690000
0#
#1695000
b10 2
1#
#1696000
b110110000000110101100111010011 $
b10011111011011111100111011000 )
b10101000 '
b10 &
#1700000
0#
#1705000
b10 2
1#
#1706000
b111100000001011101010101001000 $
b11111010000110111111111010101111 )
b10101001 '
b10 &
#1710000
0#
#1715000
b10 2
1#
#1716000
b10101001001111101111101010011100 $
b1010011001111100101010111011110 )
b10101010 '
b10 &
#1720000
0#
#1725000
b10 2
1#
#1726000
b10111110010111111111011010000110 $
b10111011110001010111010011101010 )
b10101011 '
b10 &
#1730000
0#
#1735000
b10 2
1#
#1736000
b11111110100000101100110110011001 $
b1010001011011011100111011100001 )
b10101100 '
b10 &
#1740000
0#
#1745000
b10 2
1#
#1746000
b1010110100000010011000101000000 $
b1000001000001100111111000100001 )
b10101101 '
b10 &
#1750000
0#
#1755000
b10 2
1#
#1756000
b1111111101010011110011011001001 $
b1100101100010000010101110010100 )
b10101110 '
b10 &
#1760000
0#
#1765000
b10 2
1#
#1766000
b100100100010011001000100110010 $
b101101011011000000100101010001 )
b10101111 '
b10 &
#1770000
0#
#1775000
b10 2
1#
#1776000
b1100000000011111101111001100011 $
b11000011010101001001011011000101 )
b10110000 '
b10 &
#1780000
0#
#1785000
b10 2
1#
#1786000
b101011011110001010111000100000 $
b11100011101111011000001111000010 )
b10110001 '
b10 &
#1790000
0#
#1795000
b10 2
1#
#1796000
b11100101010111010111101111000000 $
b11101001001010101001111010111110 )
b10110010 '
b10 &
#1800000
0#
#1805000
b10 2
1#
#1806000
b11101100010011101100000011100 $
b1110100011101000010010010010 )
b10110011 '
b10 &
#1810000
0#
#1815000
b10 2
1#
#1816000
b11101010010001010111101001111111 $
b11110111110000110010000001111001 )
b10110100 '
b10 &
#1820000
0#
#1825000
b10 2
1#
#1826000
b1000101111100110011001000001111 $
b11100100010111011010011110111010 )
b10110101 '
b10 &
#1830000
0#
#1835000
b10 2
1#
#1836000
b1011011110001110111011000110010 $
b1010101111010101011100100010110 )
b10110110 '
b10 &
#1840000
0#
#1845000
b10 2
1#
#1846000
b11000100001011010000011010101011 $
b10101001011001111101011110010 )
b10110111 '
b10 &
#1850000
0#
#1855000
b10 2
1#
